wowsunpack/__init__.py
wowsunpack/__main__.py
wowsunpack/params.py
wowsunpack/wowsunpack.exe
wowsunpack-0.1.10.dist-info/licenses/LICENSE
wowsunpack-0.1.10.dist-info/METADATA
wowsunpack-0.1.10.dist-info/WHEEL
wowsunpack-0.1.10.dist-info/top_level.txt
wowsunpack-0.1.10.dist-info/RECORD
