Metadata-Version: 2.4
Name: wowsunpack
Version: 0.1.10
Summary: Unpack World of Warships game params to JSON
Author-email: Yiheng Quan <development.henryquan@gmail.com>
Project-URL: Homepage, https://github.com/wowsinfo/wows_unpack
Keywords: wows,wws,unpack,params
Classifier: Programming Language :: Python :: 3
Classifier: License :: OSI Approved :: GNU Affero General Public License v3
Classifier: Operating System :: Microsoft :: Windows
Classifier: Topic :: Utilities
Requires-Python: >=3.6
License-File: LICENSE
Requires-Dist: gnu-mo-files
Dynamic: license-file
